bach/__init__.py
bach/_bach.py
bach/actions.py
bach/api_actors.py
bach/exclusion_specification.py
bach/notifications_channel.py
bach/parsers.py
bach/queries.py
bach/report_fetcher.py
bach/rules_parser.py
bach/tasks.py
bach/adapters/__init__.py
bach/adapters/repositories.py
bach/entrypoints/__init__.py
bach/entrypoints/cli.py
bach/entrypoints/server.py
bach/fetching/entity.py
bach/fetching/settings.py
bach/plugins/__init__.py
bach/plugins/youtube.py
bach/plugins/placement_exclusion/__init__.py
bach/plugins/placement_exclusion/placement_excluder.py
bach/plugins/placement_exclusion/search_term_excluder.py
bach_googleads-0.0.0.dist-info/licenses/LICENSE.txt
bach_googleads-0.0.0.dist-info/METADATA
bach_googleads-0.0.0.dist-info/WHEEL
bach_googleads-0.0.0.dist-info/entry_points.txt
bach_googleads-0.0.0.dist-info/top_level.txt
bach_googleads-0.0.0.dist-info/RECORD
