Metadata-Version: 2.4
Name: bach-googleads
Version: 0.0.0
Summary: Manages tasks in Google Ads
Author-email: "Google Inc. (gTech gPS CSE team)" <no-reply@google.com>
License: Apache 2.0
Classifier: Development Status :: 4 - Beta
Classifier: Programming Language :: Python
Requires-Python: >=3.8
License-File: LICENSE.txt
Requires-Dist: google-ads-api-report-fetcher[pandas]
Requires-Dist: croniter
Requires-Dist: sqlalchemy>2
Requires-Dist: garf_core
Requires-Dist: garf_youtube_data_api
Provides-Extra: server
Requires-Dist: fastapi[standard]; extra == "server"
Provides-Extra: all
Requires-Dist: bach[server]; extra == "all"
Dynamic: license-file
